gfe/__init__.py
gfe-0.0.1.dist-info/LICENSE
gfe-0.0.1.dist-info/METADATA
gfe-0.0.1.dist-info/WHEEL
gfe-0.0.1.dist-info/top_level.txt
gfe-0.0.1.dist-info/RECORD
