Metadata-Version: 2.1
Name: gfe
Version: 0.0.1
Summary: GFE
Home-page: https://github.com/nmdp-bioinformatics/GFE
Author: Pradeep Bashyal
Author-email: pbashyal@nmdp.org
License: UNKNOWN
Platform: UNKNOWN
Classifier: Programming Language :: Python :: 3
Classifier: License :: OSI Approved :: GNU Lesser General Public License v3 (LGPLv3)
Classifier: Operating System :: OS Independent
Requires-Python: >=3.7
